FluentCardWidget/CustomCardWidget.py
FluentCardWidget/Demo.py
FluentCardWidget/__init__.py
FluentCardWidget-1.0.2.dist-info/METADATA
FluentCardWidget-1.0.2.dist-info/WHEEL
FluentCardWidget-1.0.2.dist-info/top_level.txt
FluentCardWidget-1.0.2.dist-info/RECORD
