Metadata-Version: 2.1
Name: FluentCardWidget
Version: 1.0.2
Author: Mikuas
Requires-Dist: PySide6
Requires-Dist: PySide6-Fluent-Widgets[full]
